searchly/__init__.py
searchly/base.py
searchly/exceptions.py
searchly/log.py
searchly/providers/__init__.py
searchly/providers/brave_provider/__init__.py
searchly/providers/brave_provider/client.py
searchly/providers/dataforseo_provider/__init__.py
searchly/providers/dataforseo_provider/dataforseo.py
searchly/providers/exa_provider/__init__.py
searchly/providers/exa_provider/exa.py
searchly/providers/jigsawstack_provider/__init__.py
searchly/providers/jigsawstack_provider/jigsawstack.py
searchly/providers/kagi_provider/__init__.py
searchly/providers/kagi_provider/client.py
searchly/providers/linkup_provider/__init__.py
searchly/providers/linkup_provider/client.py
searchly/providers/search1_provider/__init__.py
searchly/providers/search1_provider/client.py
searchly/providers/serpapi_provider/__init__.py
searchly/providers/serpapi_provider/client.py
searchly/providers/serper_provider/__init__.py
searchly/providers/serper_provider/client.py
searchly/providers/tavily_provider/__init__.py
searchly/providers/tavily_provider/client.py
searchly/providers/you_provider/__init__.py
searchly/providers/you_provider/you.py
searchly/py.typed
searchly_config/__init__.py
searchly_config/configs.py
searchly_config/py.typed
searchly-2.1.0.dist-info/licenses/LICENSE
searchly-2.1.0.dist-info/WHEEL
searchly-2.1.0.dist-info/METADATA
searchly-2.1.0.dist-info/RECORD
