Metadata-Version: 2.4
Name: searchly
Version: 2.1.0
Summary: Search tools for agents
Keywords: 
Author: Philipp Temminghoff
Author-email: Philipp Temminghoff <philipptemminghoff@googlemail.com>
License-Expression: MIT
License-File: LICENSE
Classifier: Development Status :: 4 - Beta
Classifier: Framework :: Pydantic
Classifier: Framework :: Pydantic :: 2
Classifier: Intended Audience :: Developers
Classifier: Operating System :: OS Independent
Classifier: Programming Language :: Python :: 3
Classifier: Programming Language :: Python :: 3 :: Only
Classifier: Programming Language :: Python :: 3.12
Classifier: Programming Language :: Python :: 3.13
Classifier: Programming Language :: Python :: 3.14
Classifier: Topic :: Documentation
Classifier: Topic :: Software Development
Classifier: Topic :: Utilities
Classifier: Typing :: Typed
Requires-Dist: anyenv[httpx]>=0.4.4
Requires-Dist: pydantic
Requires-Dist: schemez>=2.1.5
Requires-Dist: universal-pathlib>=0.2.6
Requires-Dist: brave-search-python-client ; extra == 'all'
Requires-Dist: psutil ; extra == 'all'
Requires-Dist: exa-py ; extra == 'all'
Requires-Dist: brave-search-python-client ; extra == 'brave-search-python-client'
Requires-Dist: psutil ; extra == 'brave-search-python-client'
Requires-Dist: exa-py ; extra == 'exa'
Requires-Python: >=3.13
Project-URL: Code coverage, https://app.codecov.io/gh/phil65/searchly
Project-URL: Discussions, https://github.com/phil65/searchly/discussions
Project-URL: Documentation, https://phil65.github.io/searchly/
Project-URL: Issues, https://github.com/phil65/searchly/issues
Project-URL: Source, https://github.com/phil65/searchly
Provides-Extra: all
Provides-Extra: brave-search-python-client
Provides-Extra: exa
